aiostomp/__init__.py
aiostomp/aiostomp.py
aiostomp/errors.py
aiostomp/frame.py
aiostomp/heartbeat.py
aiostomp/protocol.py
aiostomp/subscription.py
aiostomp/test_utils.py
aiostomp-1.7.3.dist-info/METADATA
aiostomp-1.7.3.dist-info/WHEEL
aiostomp-1.7.3.dist-info/top_level.txt
aiostomp-1.7.3.dist-info/RECORD
