Metadata-Version: 2.1
Name: aiostomp
Version: 1.7.3
Summary: Stompt Client for Asyncio applications
Author: Pedro Kiefer
Author-email: Pedro Kiefer <pedro@kiefer.com.br>
License: MIT
Project-URL: Source Code, https://github.com/pedrokiefer/aiostomp
Keywords: stomp,asyncio,client
Classifier: Development Status :: 5 - Production/Stable
Classifier: Intended Audience :: Developers
Classifier: Intended Audience :: Information Technology
Classifier: Programming Language :: Python :: 3.6
Classifier: Programming Language :: Python :: 3.7
Classifier: Programming Language :: Python :: 3.8
Classifier: Programming Language :: Python :: 3.9
Classifier: Programming Language :: Python :: 3.10
Classifier: Programming Language :: Python :: 3.11
Requires-Python: >=3.6
Requires-Dist: six
Requires-Dist: async-timeout
Provides-Extra: tests
Requires-Dist: mock ; extra == 'tests'
Requires-Dist: coverage ; extra == 'tests'
Requires-Dist: asynctest ; extra == 'tests'
Requires-Dist: pytest ; extra == 'tests'
Requires-Dist: pytest-cov ; extra == 'tests'
Requires-Dist: flake8 ; extra == 'tests'
Requires-Dist: bumpversion ; extra == 'tests'
